rag_ssistant/__init__.py
rag_ssistant/cli.py
rag_ssistant/ui.py
rag_ssistant/agent/__init__.py
rag_ssistant/agent/mistral.py
rag_ssistant/chuncker/__init__.py
rag_ssistant/chuncker/text_chuncker.py
rag_ssistant/config/__init__.py
rag_ssistant/config/prompt_template.txt
rag_ssistant/db/__init__.py
rag_ssistant/db/persistant_db.py
rag_ssistant-0.1.1.dist-info/METADATA
rag_ssistant-0.1.1.dist-info/WHEEL
rag_ssistant-0.1.1.dist-info/entry_points.txt
rag_ssistant-0.1.1.dist-info/RECORD
