Metadata-Version: 2.4
Name: rag-ssistant
Version: 0.1.1
Summary: RAGssistant: A RAG Assistant for your tasks
Requires-Python: >=3.11
Requires-Dist: accelerate>=1.7.0
Requires-Dist: chromadb>=1.0.12
Requires-Dist: gradio>=5.33.1
Requires-Dist: hf-xet>=1.1.3
Requires-Dist: huggingface-hub>=0.31.2
Requires-Dist: langchain-community>=0.3.24
Requires-Dist: langchain-huggingface>=0.2.0
Requires-Dist: langchain-mistralai>=0.2.10
Requires-Dist: langchain-text-splitters>=0.3.8
Requires-Dist: langgraph>=0.4.5
Requires-Dist: pydantic>=2.11.4
Requires-Dist: pypdf>=5.5.0
Requires-Dist: sentence-transformers>=4.1.0
